pykin/__init__.py
pykin/_version.py
pykin/assets/__init__.py
pykin/assets/__pycache__/__init__.cpython-38.pyc
pykin/assets/config/baxter_init_params.yaml
pykin/assets/config/doosan_init_params.yaml
pykin/assets/config/iiwa14_init_params.yaml
pykin/assets/config/iiwa7_init_params.yaml
pykin/assets/config/panda_init_params.yaml
pykin/assets/config/sawyer_init_params.yaml
pykin/assets/config/ur5e_init_params.yaml
pykin/assets/objects/arch_box.xml
pykin/assets/objects/ben_cubeA.xml
pykin/assets/objects/ben_cubeB.xml
pykin/assets/objects/ben_cubeC.xml
pykin/assets/objects/ben_cubeD.xml
pykin/assets/objects/ben_cubeE.xml
pykin/assets/objects/ben_cubeF.xml
pykin/assets/objects/ben_cubeG.xml
pykin/assets/objects/ben_cubeH.xml
pykin/assets/objects/ben_cubeI.xml
pykin/assets/objects/ben_cubeJ.xml
pykin/assets/objects/ben_table.xml
pykin/assets/objects/ben_table_ceiling.xml
pykin/assets/objects/ben_tray_blue.xml
pykin/assets/objects/ben_tray_red.xml
pykin/assets/objects/bin.xml
pykin/assets/objects/bottle.xml
pykin/assets/objects/bread-visual.xml
pykin/assets/objects/bread.xml
pykin/assets/objects/can-visual.xml
pykin/assets/objects/can.xml
pykin/assets/objects/cereal-visual.xml
pykin/assets/objects/cereal.xml
pykin/assets/objects/clearbox.xml
pykin/assets/objects/clearbox_org.xml
pykin/assets/objects/custom_cylinder.xml
pykin/assets/objects/custom_table.xml
pykin/assets/objects/door.xml
pykin/assets/objects/door_lock.xml
pykin/assets/objects/goal_box.xml
pykin/assets/objects/hanoi_disk.xml
pykin/assets/objects/hanoi_disk_old.xml
pykin/assets/objects/hanoi_peg.xml
pykin/assets/objects/lemon.xml
pykin/assets/objects/milk-visual.xml
pykin/assets/objects/milk.xml
pykin/assets/objects/plate-with-hole.xml
pykin/assets/objects/round-nut.xml
pykin/assets/objects/shelf.xml
pykin/assets/objects/shelf_old.xml
pykin/assets/objects/square-nut.xml
pykin/assets/objects/square_box.xml
pykin/assets/objects/meshes/arch_box.stl
pykin/assets/objects/meshes/arch_box_0.stl
pykin-1.6.0.dist-info/LICENSE
pykin-1.6.0.dist-info/METADATA
pykin-1.6.0.dist-info/WHEEL
pykin-1.6.0.dist-info/eager_resources.txt
pykin-1.6.0.dist-info/top_level.txt
pykin-1.6.0.dist-info/RECORD
