Metadata-Version: 2.1
Name: pykin
Version: 1.6.0
Summary: Robotics Kinematics Library
Home-page: https://github.com/jdj2261/pykin.git
Author: Daejong Jin, Youngtaek Hong, Juhan Park
Author-email: wlseoeo@gmail.com
License: UNKNOWN
Download-URL: https://github.com/jdj2261/pykin/archive/refs/heads/main.zip
Platform: UNKNOWN
Requires-Python: >=3
License-File: LICENSE
Requires-Dist: numpy
Requires-Dist: matplotlib
Requires-Dist: trimesh[easy]
Requires-Dist: pyglet
Requires-Dist: tqdm
Requires-Dist: pyyaml
Requires-Dist: python-fcl
Requires-Dist: Pillow
